clientmonitor/Client.py
clientmonitor/Errors.py
clientmonitor/Message.py
clientmonitor/Server.py
clientmonitor/__init__.py
clientmonitor-0.1.0.dist-info/METADATA
clientmonitor-0.1.0.dist-info/WHEEL
clientmonitor-0.1.0.dist-info/licenses/LICENSE
clientmonitor-0.1.0.dist-info/RECORD
