Metadata-Version: 2.3
Name: clientmonitor
Version: 0.1.0
Summary: Collect client data and display on monitor
Project-URL: Homepage, https://github.com/stylesuxx/clientmonitor
Project-URL: Issues, https://github.com/stylesuxx/pyntercom/clientmonitor
Author-email: "Chris L." <stylesuxx@gmail.com>
License-File: LICENSE
Classifier: License :: OSI Approved :: MIT License
Classifier: Operating System :: OS Independent
Classifier: Programming Language :: Python :: 3
Requires-Python: >=3.8
